[{"id":172,"party":"Independent","constituency":"Hackney North and Stoke Newington","name":"Ms Diane Abbott","party_color":"808080"},{"constituency":"Ipswich","party":"Labour (Co-op)","party_color":"808080","name":"Jack Abbott","id":5131},{"id":4212,"party_color":"808080","name":"Debbie Abrahams","party":"Labour","constituency":"Oldham East and Saddleworth"},{"name":"Shockat Adam","party_color":"808080","party":"Independent","constituency":"Leicester South","id":5120},{"id":5213,"party":"Labour","constituency":"Glasgow South West","party_color":"808080","name":"Dr Zubir Ahmed"},{"party_color":"808080","name":"Luke Akehurst","party":"Labour","constituency":"North Durham","id":5112},{"name":"Mr Bayo Alaba","party_color":"808080","party":"Labour","constituency":"Southend East and Rochford","id":5097},{"name":"Dan Aldridge","party_color":"808080","constituency":"Weston-super-Mare","party":"Labour","id":5172},{"id":632,"party_color":"808080","name":"Mr Douglas Alexander","party":"Labour (Co-op)","constituency":"Lothian East"},{"party_color":"808080","name":"Heidi Alexander","party":"Labour","constituency":"Swindon South","id":4038},{"constituency":"North Somerset","party":"Labour","party_color":"808080","name":"Sadik Al-Hassan","id":5312},{"id":4138,"party":"Labour","constituency":"Bethnal Green and Stepney","party_color":"808080","name":"Rushanara Ali"},{"id":4747,"party":"Labour","constituency":"Birmingham Hall Green and Moseley","name":"Tahir Ali","party_color":"808080"},{"id":4573,"party":"Labour","constituency":"Tooting","party_color":"808080","name":"Dr Rosena Allin-Khan"},{"id":5356,"constituency":"North Antrim","party":"Traditional Unionist Voice","name":"Jim Allister","party_color":"808080"},{"party":"Liberal Democrat","constituency":"Taunton and Wellington","name":"Gideon Amos","party_color":"808080","id":5250},{"name":"Callum Anderson","party_color":"808080","party":"Labour","constituency":"Buckingham and Bletchley","id":5193},{"id":4788,"party":"Labour","constituency":"Putney","party_color":"808080","name":"Fleur Anderson"},{"party":"Reform UK","constituency":"Ashfield","party_color":"808080","name":"Lee Anderson","id":4743},{"id":4742,"name":"Stuart Anderson","party_color":"808080","party":"Conservative","constituency":"South Shropshire"}]