[{"constituency":"Hackney North and Stoke Newington","name":"Ms Diane Abbott","party":"Independent","party_color":"808080","id":172},{"name":"Jack Abbott","party":"Labour (Co-op)","constituency":"Ipswich","id":5131,"party_color":"808080"},{"id":4212,"party_color":"808080","party":"Labour","name":"Debbie Abrahams","constituency":"Oldham East and Saddleworth"},{"id":5120,"party_color":"808080","party":"Independent","name":"Shockat Adam","constituency":"Leicester South"},{"party":"Labour","name":"Dr Zubir Ahmed","constituency":"Glasgow South West","id":5213,"party_color":"808080"},{"id":5112,"party_color":"808080","name":"Luke Akehurst","party":"Labour","constituency":"North Durham"},{"constituency":"Southend East and Rochford","party":"Labour","name":"Mr Bayo Alaba","party_color":"808080","id":5097},{"party":"Labour","name":"Dan Aldridge","constituency":"Weston-super-Mare","id":5172,"party_color":"808080"},{"id":632,"party_color":"808080","constituency":"Lothian East","name":"Mr Douglas Alexander","party":"Labour (Co-op)"},{"party_color":"808080","id":4038,"party":"Labour","name":"Heidi Alexander","constituency":"Swindon South"},{"party_color":"808080","id":5312,"constituency":"North Somerset","name":"Sadik Al-Hassan","party":"Labour"},{"id":4138,"party_color":"808080","constituency":"Bethnal Green and Stepney","name":"Rushanara Ali","party":"Labour"},{"id":4747,"party_color":"808080","party":"Labour","name":"Tahir Ali","constituency":"Birmingham Hall Green and Moseley"},{"party_color":"808080","id":4573,"constituency":"Tooting","party":"Labour","name":"Dr Rosena Allin-Khan"},{"party_color":"808080","id":5356,"constituency":"North Antrim","party":"Traditional Unionist Voice","name":"Jim Allister"},{"party_color":"808080","id":5250,"constituency":"Taunton and Wellington","party":"Liberal Democrat","name":"Gideon Amos"},{"id":5193,"party_color":"808080","constituency":"Buckingham and Bletchley","party":"Labour","name":"Callum Anderson"},{"constituency":"Putney","name":"Fleur Anderson","party":"Labour","id":4788,"party_color":"808080"},{"name":"Lee Anderson","party":"Reform UK","constituency":"Ashfield","party_color":"808080","id":4743},{"party":"Conservative","name":"Stuart Anderson","constituency":"South Shropshire","party_color":"808080","id":4742}]